pytest_pyppeteer/__init__.py
pytest_pyppeteer/page.py
pytest_pyppeteer/plugin.py
pytest_pyppeteer-0.3.1.dist-info/entry_points.txt
pytest_pyppeteer-0.3.1.dist-info/LICENSE
pytest_pyppeteer-0.3.1.dist-info/WHEEL
pytest_pyppeteer-0.3.1.dist-info/METADATA
pytest_pyppeteer-0.3.1.dist-info/RECORD
