Metadata-Version: 2.1
Name: pytest-pyppeteer
Version: 0.3.1
Summary: A plugin to run pyppeteer in pytest
Home-page: https://github.com/luizyao/pytest-pyppeteer/
License: MIT
Author: Luiz Yao
Author-email: luizyao@163.com
Requires-Python: >=3.7,<4.0
Classifier: License :: OSI Approved :: MIT License
Classifier: Programming Language :: Python :: 3
Classifier: Programming Language :: Python :: 3.10
Classifier: Programming Language :: Python :: 3.7
Classifier: Programming Language :: Python :: 3.8
Classifier: Programming Language :: Python :: 3.9
Requires-Dist: cssselect (>=1.1.0,<2.0.0)
Requires-Dist: lxml (>=4.7.1,<5.0.0)
Requires-Dist: pyppeteer (>=1.0.2,<2.0.0)
Requires-Dist: pytest (>=6.2.5,<7.0.0)
Project-URL: Bug Tracker, https://github.com/luizyao/pytest-pyppeteer/issues
Project-URL: Documentation, https://github.com/luizyao/pytest-pyppeteer/blob/dev/README.md
Project-URL: Repository, https://github.com/luizyao/pytest-pyppeteer/
